{
    "piped": [
        "https://nyc1.iv.ggtyler.dev",
        "https://lekker.gay",
        "https://iv.duti.dev",
        "https://pol1.iv.ggtyler.dev",
        "https://cal1.iv.ggtyler.dev",
        "https://invidious.adminforge.de",
        "https://id.420129.xyz",
        "https://invidious.reallyaweso.me",
        "https://invidious.nikkosphere.com",
        "https://iv.ggtyler.dev"
    ],
    "hls": [],
    "invidious": [
        "https://invidious.nikkosphere.com",
        "https://cal1.iv.ggtyler.dev"
    ],
    "hyperpipe": "https://hyperpipeapi.darkness.services",
    "status": 0
}