{
    "piped": [
        "https://invidious.reallyaweso.me",
        "https://invidious.darkness.services",
        "https://invidious.private.coffee",
        "https://invidious.schenkel.eti.br",
        "https://invidious.nikkosphere.com",
        "https://lekker.gay",
        "https://nyc1.iv.ggtyler.dev",
        "https://cal1.iv.ggtyler.dev",
        "https://invidious.adminforge.de",
        "https://iv.ggtyler.dev",
        "https://invidious.f5.si",
        "https://inv.stealthy.club",
        "https://pol1.iv.ggtyler.dev"
    ],
    "hls": [],
    "invidious": [
        "https://invidious.f5.si"
    ],
    "hyperpipe": "https://hyperpipeapi.darkness.services",
    "status": 0
}